kaihoplots/__init__.py
kaihoplots/presentation.mplstyle
kaihoplots-0.0.1.dist-info/METADATA
kaihoplots-0.0.1.dist-info/WHEEL
kaihoplots-0.0.1.dist-info/top_level.txt
kaihoplots-0.0.1.dist-info/RECORD
