Metadata-Version: 2.1
Name: kaihoplots
Version: 0.0.1
Summary: Kaiho Stylesheet for matplotlib
